majiang/__init__.py
majiang/board.py
majiang/consts.py
majiang/game_tile_manager.py
majiang/gui_example.py
majiang/tile.py
majiang/tile_field.py
majiang/graphics/__init__.py
majiang/graphics/game.py
majiang/graphics/tile.py
majiang/graphics/tile_field.py
python_majiang-0.0.1.dist-info/METADATA
python_majiang-0.0.1.dist-info/WHEEL
python_majiang-0.0.1.dist-info/top_level.txt
python_majiang-0.0.1.dist-info/RECORD
