Metadata-Version: 2.1
Name: python-majiang
Version: 0.0.1
Summary: A library for MCR(Mahjong Competition Rules) game log generation.
Home-page: https://github.com/otobear/python-majiang
Author: ZUO Yong
Author-email: spacedogsergei@gmail.com
License: MIT
Keywords: majiang mahjong mcr
